admin/__init__.py
admin/base.py
txAWS-0.4.0.data/scripts/aws-status
txAWS-0.4.0.data/scripts/txaws-create-bucket
txAWS-0.4.0.data/scripts/txaws-delete-bucket
txAWS-0.4.0.data/scripts/txaws-delete-object
txAWS-0.4.0.data/scripts/txaws-discover
txAWS-0.4.0.data/scripts/txaws-get-bucket
txAWS-0.4.0.data/scripts/txaws-get-object
txAWS-0.4.0.data/scripts/txaws-head-object
txAWS-0.4.0.data/scripts/txaws-list-buckets
txAWS-0.4.0.data/scripts/txaws-put-object
txAWS-0.4.0.dist-info/DESCRIPTION.rst
txAWS-0.4.0.dist-info/METADATA
txAWS-0.4.0.dist-info/RECORD
txAWS-0.4.0.dist-info/WHEEL
txAWS-0.4.0.dist-info/metadata.json
txAWS-0.4.0.dist-info/top_level.txt
txaws/__init__.py
txaws/_auth_v4.py
txaws/credentials.py
txaws/exception.py
txaws/meta.py
txaws/reactor.py
txaws/regions.py
txaws/script.py
txaws/service.py
txaws/util.py
txaws/version.py
txaws/wsdl.py
txaws/client/__init__.py
txaws/client/_producers.py
txaws/client/_validators.py
txaws/client/base.py
txaws/client/ssl.py
txaws/client/discover/__init__.py
txaws/client/discover/command.py
txaws/client/discover/entry_point.py
txaws/client/discover/tests/__init__.py
txaws/client/discover/tests/test_command.py
txaws/client/discover/tests/test_entry_point.py
txaws/client/gui/__init__.py
txaws/client/gui/gtk.py
txaws/client/gui/tests/__init__.py
txaws/client/gui/tests/test_gtk.py
txaws/client/tests/__init__.py
txaws/client/tests/badprivate.ssl
txaws/client/tests/badpublic.ssl
txaws/client/tests/private.ssl
txaws/client/tests/private_san.ssl
txaws/client/tests/public.ssl
txaws/client/tests/public_san.ssl
txaws/client/tests/test_base.py
txaws/client/tests/test_ssl.py
txaws/ec2/__init__.py
txaws/ec2/client.py
txaws/ec2/exception.py
txaws/ec2/model.py
txaws/ec2/tests/__init__.py
txaws/ec2/tests/test_client.py
txaws/ec2/tests/test_exception.py
txaws/ec2/tests/test_model.py
txaws/route53/__init__.py
txaws/route53/_util.py
txaws/route53/client.py
txaws/route53/interface.py
txaws/route53/model.py
txaws/route53/tests/__init__.py
txaws/route53/tests/test_model.py
txaws/route53/tests/test_route53.py
txaws/route53/tests/test_util.py
txaws/s3/__init__.py
txaws/s3/acls.py
